lifegraph/__init__.py
lifegraph/configuration.py
lifegraph/lifegraph.py
lifegraph-0.1.0.dist-info/licenses/LICENSE
lifegraph-0.1.0.dist-info/WHEEL
lifegraph-0.1.0.dist-info/METADATA
lifegraph-0.1.0.dist-info/RECORD
