Metadata-Version: 2.4
Name: lifegraph
Version: 0.1.0
Summary: A package to visualize your life as a grid of weeks.
Author-email: Kyle Shores <kyleshores@gmail.com>
Requires-Python: >=3.7
License-Expression: MIT
License-File: LICENSE
Requires-Dist: matplotlib>=3.0
Requires-Dist: numpy>=1.17
Requires-Dist: python-dateutil>=2.8
Requires-Dist: pytest ; extra == "dev"
Requires-Dist: pytest-cov ; extra == "dev"
Project-URL: Homepage, https://github.com/kyleshores/Life-Graph
Provides-Extra: dev
